<lista_mensajes><mensaje>
        Lugar y fecha: Guatemala, 29/10/2024 16:33 Usuario: @P3rs0n4
        Red social: Instagram El d&#237;a de hoy, fui a una tienda de Nike, muy lamentable porque cobran mal ya que los empleados no se encuentan capacidatos. De verdad espero arreglen esto, me siento #enojado.
    </mensaje><mensaje>
        Lugar y fecha: Guatemala, 29/10/2024
        Usuario: Princess01
        Red social: X Maravilloso el servicio de Walmart, su la persona que me atendi&#243; de verdad sab&#237;a lo que hac&#237;a.
    </mensaje><mensaje>
        Lugar y fecha: Filadelfia, 01/11/2024 
        Usuario: Xx$$Money$$xX
        Red social: Facebook 
        Quiero compartirles que en ADIDAS me han vendido unos pants, honestamente, aunque ha sido bueno el precio con el que los consegu&#237; ah&#237;, siento que ha sido algo deficiente su tiempo de servicio.
    </mensaje><mensaje>
        Lugar y fecha: Detroit, 02/11/2024 
        Usuario: user@correo.com
        Red social: Facebook 
        A mi me ha encantado como me han atendido hoy en Walmart, &#161;Espero que su servicio siga as&#237;!
    </mensaje><mensaje>
        Lugar y fecha: Detroit, 02/11/2024 
        Usuario: user@correo.com
        Red social: Facebook 
        Solo quiero decir que ha sido excelente como Adidas me ha vendido las cosas, igualmente, muy maravilloso como en Nike me han cobrado r&#225;pidamente.
    </mensaje></lista_mensajes>